ekorpkit/__init__.py
ekorpkit/_version.py
ekorpkit/base.py
ekorpkit/cli.py
ekorpkit/config.py
ekorpkit/ekonf.py
ekorpkit/run.py
ekorpkit/conf/__init__.py
ekorpkit/conf/config.yaml
ekorpkit/conf/ekonf.yaml
ekorpkit/conf/run.yaml
ekorpkit/conf/_eval_/automl_classification.yaml
ekorpkit/conf/_eval_/classification.yaml
ekorpkit/conf/_eval_/simple_classification.yaml
ekorpkit/conf/_eval_/simple_t5_classification.yaml
ekorpkit/conf/_func_/aggregate_columns.yaml
ekorpkit/conf/_func_/aggregate_scores.yaml
ekorpkit/conf/_func_/chunk.yaml
ekorpkit/conf/_func_/combine_columns.yaml
ekorpkit/conf/_func_/concat_dataframes.yaml
ekorpkit/conf/_func_/drop.yaml
ekorpkit/conf/_func_/drop_duplicates.yaml
ekorpkit/conf/_func_/eval_columns.yaml
ekorpkit/conf/_func_/evaluate_classification_performance.yaml
ekorpkit/conf/_func_/explode_splits.yaml
ekorpkit/conf/_func_/extract_tokens.yaml
ekorpkit/conf/_func_/fillna.yaml
ekorpkit/conf/_func_/filter_length.yaml
ekorpkit/conf/_func_/filter_query.yaml
ekorpkit/conf/_func_/general_function.yaml
ekorpkit/conf/_func_/load_dataframe.yaml
ekorpkit/conf/_func_/melt.yaml
ekorpkit/conf/_func_/merge_dataframe.yaml
ekorpkit/conf/_func_/normalize.yaml
ekorpkit/conf/_func_/pivot.yaml
ekorpkit/conf/_func_/plot.yaml
ekorpkit/conf/_func_/predict.yaml
ekorpkit/conf/_func_/remove_startswith.yaml
ekorpkit/conf/_func_/rename_columns.yaml
ekorpkit/conf/_func_/reset_index.yaml
ekorpkit/conf/_func_/sampling.yaml
ekorpkit/conf/_func_/save_as_json.yaml
ekorpkit/conf/_func_/save_as_text.yaml
ekorpkit/conf/_func_/save_dataframe.yaml
ekorpkit/conf/_func_/save_metadata.yaml
ekorpkit/conf/_func_/save_samples.yaml
ekorpkit/conf/_func_/segment.yaml
ekorpkit/conf/_func_/split_column.yaml
ekorpkit/conf/_func_/split_dataframe.yaml
ekorpkit/conf/_func_/split_sampling.yaml
ekorpkit/conf/_func_/stdout_samples.yaml
ekorpkit/conf/_func_/subset.yaml
ekorpkit/conf/_func_/summary_stats.yaml
ekorpkit/conf/_func_/tokenize.yaml
ekorpkit/conf/_func_/top_values.yaml
ekorpkit-0.1.40.dist-info/LICENSE
ekorpkit-0.1.40.dist-info/METADATA
ekorpkit-0.1.40.dist-info/WHEEL
ekorpkit-0.1.40.dist-info/entry_points.txt
ekorpkit-0.1.40.dist-info/top_level.txt
ekorpkit-0.1.40.dist-info/RECORD
