Metadata-Version: 2.1
Name: ekorpkit
Version: 0.1.40
Summary: eKorpkit provides a flexible interface for NLP and ML research pipelines such as extraction, transformation, tokenization, training, and visualization.
Home-page: https://github.com/entelecheia/ekorpkit
Author: Young Joon Lee
License: UNKNOWN
Platform: UNKNOWN
Requires-Python: >=3.7
Requires-Dist: numpy
Requires-Dist: tqdm
Requires-Dist: pandas
Requires-Dist: hydra-core (>=1.2.0)
Requires-Dist: hydra-colorlog
Requires-Dist: pydantic
Requires-Dist: python-dotenv
Requires-Dist: gdown
Requires-Dist: chardet
Requires-Dist: rehash
Requires-Dist: requests
Requires-Dist: scipy
Requires-Dist: pytablewriter (>=0.64.0)
Requires-Dist: ftfy
Requires-Dist: requests (<3.0,>=2.0)
Requires-Dist: rich (>=11.1)
Requires-Dist: filelock (<3.8,>=3.4)
Requires-Dist: huggingface-hub (>=0.8.1)
Requires-Dist: dataclasses ; python_version < "3.7"
Provides-Extra: pillow
Requires-Dist: Pillow (<9.1.0) ; extra == 'pillow'
Provides-Extra: accelerate
Requires-Dist: accelerate ; extra == 'accelerate'
Provides-Extra: all
Requires-Dist: pysbd ; extra == 'all'
Requires-Dist: lsh ; extra == 'all'
Requires-Dist: jsonpath-ng ; extra == 'all'
Requires-Dist: tensorflow ; extra == 'all'
Requires-Dist: p-tqdm ; extra == 'all'
Requires-Dist: pysimdjson ; extra == 'all'
Requires-Dist: statsmodels ; extra == 'all'
Requires-Dist: flaml ; extra == 'all'
Requires-Dist: pynori ; extra == 'all'
Requires-Dist: mecab-python3 ; extra == 'all'
Requires-Dist: emoji (<2.0) ; extra == 'all'
Requires-Dist: rich ; extra == 'all'
Requires-Dist: py7zr ; extra == 'all'
Requires-Dist: accelerate ; extra == 'all'
Requires-Dist: jsonlines ; extra == 'all'
Requires-Dist: Pillow (<9.1.0) ; extra == 'all'
Requires-Dist: dicttoxml ; extra == 'all'
Requires-Dist: scipy ; extra == 'all'
Requires-Dist: fredapi ; extra == 'all'
Requires-Dist: nasdaq-data-link ; extra == 'all'
Requires-Dist: pathos ; extra == 'all'
Requires-Dist: beautifulsoup4 ; extra == 'all'
Requires-Dist: mecab-ko-dic ; extra == 'all'
Requires-Dist: evaluate ; extra == 'all'
Requires-Dist: datasets ; extra == 'all'
Requires-Dist: wordcloud ; extra == 'all'
Requires-Dist: joblib ; extra == 'all'
Requires-Dist: pyLDAvis ; extra == 'all'
Requires-Dist: cssutils ; extra == 'all'
Requires-Dist: nltk ; extra == 'all'
Requires-Dist: fugashi ; extra == 'all'
Requires-Dist: html-to-json ; extra == 'all'
Requires-Dist: zstandard ; extra == 'all'
Requires-Dist: tomotopy ; extra == 'all'
Requires-Dist: datasketch ; extra == 'all'
Requires-Dist: matplotlib ; extra == 'all'
Requires-Dist: sacremoses ; extra == 'all'
Requires-Dist: kaleido ; extra == 'all'
Requires-Dist: soynlp ; extra == 'all'
Requires-Dist: orjson ; extra == 'all'
Requires-Dist: seaborn ; extra == 'all'
Requires-Dist: loky ; extra == 'all'
Requires-Dist: openpyxl ; extra == 'all'
Requires-Dist: cleanlab ; extra == 'all'
Requires-Dist: plotly ; extra == 'all'
Requires-Dist: wget ; extra == 'all'
Requires-Dist: simpletransformers (>=0.63) ; extra == 'all'
Provides-Extra: art
Requires-Dist: flax ; extra == 'art'
Requires-Dist: timm ; extra == 'art'
Requires-Dist: unidecode ; extra == 'art'
Requires-Dist: jax ; extra == 'art'
Requires-Dist: lpips ; extra == 'art'
Requires-Dist: einops ; extra == 'art'
Requires-Dist: opencv-python (==4.5.5.64) ; extra == 'art'
Provides-Extra: automl
Requires-Dist: flaml ; extra == 'automl'
Requires-Dist: scipy ; extra == 'automl'
Provides-Extra: aws
Requires-Dist: boto3 (<2.0,>=1.0) ; extra == 'aws'
Provides-Extra: beautifulsoup4
Requires-Dist: beautifulsoup4 ; extra == 'beautifulsoup4'
Provides-Extra: bok
Requires-Dist: pyhwp ; extra == 'bok'
Provides-Extra: boto3
Requires-Dist: boto3 (<2.0,>=1.0) ; extra == 'boto3'
Provides-Extra: cached-path
Requires-Dist: boto3 (<2.0,>=1.0) ; extra == 'cached-path'
Requires-Dist: huggingface-hub (<0.9.0,>=0.8.1) ; extra == 'cached-path'
Requires-Dist: google-cloud-storage (<3.0,>=1.32.0) ; extra == 'cached-path'
Provides-Extra: cleanlab
Requires-Dist: cleanlab ; extra == 'cleanlab'
Provides-Extra: cssutils
Requires-Dist: cssutils ; extra == 'cssutils'
Provides-Extra: dalle-mini
Requires-Dist: flax ; extra == 'dalle-mini'
Requires-Dist: jax ; extra == 'dalle-mini'
Provides-Extra: database
Requires-Dist: pymongo ; extra == 'database'
Provides-Extra: dataset
Requires-Dist: pysbd ; extra == 'dataset'
Requires-Dist: lsh ; extra == 'dataset'
Requires-Dist: jsonpath-ng ; extra == 'dataset'
Requires-Dist: p-tqdm ; extra == 'dataset'
Requires-Dist: pysimdjson ; extra == 'dataset'
Requires-Dist: emoji (<2.0) ; extra == 'dataset'
Requires-Dist: py7zr ; extra == 'dataset'
Requires-Dist: jsonlines ; extra == 'dataset'
Requires-Dist: pathos ; extra == 'dataset'
Requires-Dist: beautifulsoup4 ; extra == 'dataset'
Requires-Dist: datasets ; extra == 'dataset'
Requires-Dist: joblib ; extra == 'dataset'
Requires-Dist: zstandard ; extra == 'dataset'
Requires-Dist: loky ; extra == 'dataset'
Requires-Dist: tensorflow-datasets ; extra == 'dataset'
Requires-Dist: orjson ; extra == 'dataset'
Requires-Dist: openpyxl ; extra == 'dataset'
Requires-Dist: wget ; extra == 'dataset'
Requires-Dist: datasketch ; extra == 'dataset'
Provides-Extra: datasets
Requires-Dist: datasets ; extra == 'datasets'
Provides-Extra: datasketch
Requires-Dist: datasketch ; extra == 'datasketch'
Provides-Extra: ddbackend
Requires-Dist: ray ; extra == 'ddbackend'
Requires-Dist: modin ; extra == 'ddbackend'
Provides-Extra: dicttoxml
Requires-Dist: dicttoxml ; extra == 'dicttoxml'
Provides-Extra: disco
Requires-Dist: timm ; extra == 'disco'
Requires-Dist: unidecode ; extra == 'disco'
Requires-Dist: lpips ; extra == 'disco'
Requires-Dist: einops ; extra == 'disco'
Requires-Dist: opencv-python (==4.5.5.64) ; extra == 'disco'
Provides-Extra: doc
Requires-Dist: matplotlib ; extra == 'doc'
Requires-Dist: kaleido ; extra == 'doc'
Requires-Dist: rich ; extra == 'doc'
Requires-Dist: seaborn ; extra == 'doc'
Requires-Dist: plotly ; extra == 'doc'
Requires-Dist: Pillow (<9.1.0) ; extra == 'doc'
Provides-Extra: edgar
Requires-Dist: pathos ; extra == 'edgar'
Requires-Dist: cssutils ; extra == 'edgar'
Provides-Extra: einops
Requires-Dist: einops ; extra == 'einops'
Provides-Extra: emoji
Requires-Dist: emoji (<2.0) ; extra == 'emoji'
Provides-Extra: evaluate
Requires-Dist: evaluate ; extra == 'evaluate'
Provides-Extra: exhaustive
Requires-Dist: pysbd ; extra == 'exhaustive'
Requires-Dist: lsh ; extra == 'exhaustive'
Requires-Dist: spacy ; extra == 'exhaustive'
Requires-Dist: rubrix ; extra == 'exhaustive'
Requires-Dist: mail-parser ; extra == 'exhaustive'
Requires-Dist: numba ; extra == 'exhaustive'
Requires-Dist: boto3 (<2.0,>=1.0) ; extra == 'exhaustive'
Requires-Dist: jsonpath-ng ; extra == 'exhaustive'
Requires-Dist: huggingface-hub (<0.9.0,>=0.8.1) ; extra == 'exhaustive'
Requires-Dist: timm ; extra == 'exhaustive'
Requires-Dist: tensorflow ; extra == 'exhaustive'
Requires-Dist: p-tqdm ; extra == 'exhaustive'
Requires-Dist: pysimdjson ; extra == 'exhaustive'
Requires-Dist: statsmodels ; extra == 'exhaustive'
Requires-Dist: lpips ; extra == 'exhaustive'
Requires-Dist: simpletransformers (>=0.63) ; extra == 'exhaustive'
Requires-Dist: flaml ; extra == 'exhaustive'
Requires-Dist: pynori ; extra == 'exhaustive'
Requires-Dist: mecab-python3 ; extra == 'exhaustive'
Requires-Dist: emoji (<2.0) ; extra == 'exhaustive'
Requires-Dist: pymongo ; extra == 'exhaustive'
Requires-Dist: rich ; extra == 'exhaustive'
Requires-Dist: py7zr ; extra == 'exhaustive'
Requires-Dist: flax ; extra == 'exhaustive'
Requires-Dist: yellowbrick ; extra == 'exhaustive'
Requires-Dist: accelerate ; extra == 'exhaustive'
Requires-Dist: jsonlines ; extra == 'exhaustive'
Requires-Dist: Pillow (<9.1.0) ; extra == 'exhaustive'
Requires-Dist: dicttoxml ; extra == 'exhaustive'
Requires-Dist: unidecode ; extra == 'exhaustive'
Requires-Dist: scipy ; extra == 'exhaustive'
Requires-Dist: pubmed-parser ; extra == 'exhaustive'
Requires-Dist: google-cloud-storage (<3.0,>=1.32.0) ; extra == 'exhaustive'
Requires-Dist: namu-wiki-extractor ; extra == 'exhaustive'
Requires-Dist: fredapi ; extra == 'exhaustive'
Requires-Dist: nasdaq-data-link ; extra == 'exhaustive'
Requires-Dist: pathos ; extra == 'exhaustive'
Requires-Dist: wikiextractor ; extra == 'exhaustive'
Requires-Dist: ray ; extra == 'exhaustive'
Requires-Dist: beautifulsoup4 ; extra == 'exhaustive'
Requires-Dist: mecab-ko-dic ; extra == 'exhaustive'
Requires-Dist: evaluate ; extra == 'exhaustive'
Requires-Dist: datasets ; extra == 'exhaustive'
Requires-Dist: modin ; extra == 'exhaustive'
Requires-Dist: wordcloud ; extra == 'exhaustive'
Requires-Dist: joblib ; extra == 'exhaustive'
Requires-Dist: pyLDAvis ; extra == 'exhaustive'
Requires-Dist: cssutils ; extra == 'exhaustive'
Requires-Dist: fugashi ; extra == 'exhaustive'
Requires-Dist: nltk ; extra == 'exhaustive'
Requires-Dist: fasttext-langdetect ; extra == 'exhaustive'
Requires-Dist: html-to-json ; extra == 'exhaustive'
Requires-Dist: zstandard ; extra == 'exhaustive'
Requires-Dist: tomotopy ; extra == 'exhaustive'
Requires-Dist: opencv-python (==4.5.5.64) ; extra == 'exhaustive'
Requires-Dist: pdfplumber ; extra == 'exhaustive'
Requires-Dist: google-api-python-client ; extra == 'exhaustive'
Requires-Dist: matplotlib ; extra == 'exhaustive'
Requires-Dist: sacremoses ; extra == 'exhaustive'
Requires-Dist: kaleido ; extra == 'exhaustive'
Requires-Dist: soynlp ; extra == 'exhaustive'
Requires-Dist: orjson ; extra == 'exhaustive'
Requires-Dist: seaborn ; extra == 'exhaustive'
Requires-Dist: loky ; extra == 'exhaustive'
Requires-Dist: openpyxl ; extra == 'exhaustive'
Requires-Dist: cleanlab ; extra == 'exhaustive'
Requires-Dist: plotly ; extra == 'exhaustive'
Requires-Dist: tensorflow-datasets ; extra == 'exhaustive'
Requires-Dist: guesslang ; extra == 'exhaustive'
Requires-Dist: jax ; extra == 'exhaustive'
Requires-Dist: wget ; extra == 'exhaustive'
Requires-Dist: pyhwp ; extra == 'exhaustive'
Requires-Dist: einops ; extra == 'exhaustive'
Requires-Dist: datasketch ; extra == 'exhaustive'
Provides-Extra: fasttext-langdetect
Requires-Dist: fasttext-langdetect ; extra == 'fasttext-langdetect'
Provides-Extra: fetch
Requires-Dist: wget ; extra == 'fetch'
Requires-Dist: zstandard ; extra == 'fetch'
Requires-Dist: py7zr ; extra == 'fetch'
Provides-Extra: flaml
Requires-Dist: flaml ; extra == 'flaml'
Provides-Extra: flax
Requires-Dist: flax ; extra == 'flax'
Provides-Extra: fomc
Requires-Dist: nasdaq-data-link ; extra == 'fomc'
Requires-Dist: fredapi ; extra == 'fomc'
Requires-Dist: pdfplumber ; extra == 'fomc'
Requires-Dist: statsmodels ; extra == 'fomc'
Provides-Extra: fred
Requires-Dist: fredapi ; extra == 'fred'
Provides-Extra: fredapi
Requires-Dist: fredapi ; extra == 'fredapi'
Provides-Extra: fugashi
Requires-Dist: fugashi ; extra == 'fugashi'
Provides-Extra: google
Requires-Dist: google-api-python-client ; extra == 'google'
Requires-Dist: google-cloud-storage (<3.0,>=1.32.0) ; extra == 'google'
Provides-Extra: google-api-python-client
Requires-Dist: google-api-python-client ; extra == 'google-api-python-client'
Provides-Extra: google-cloud-storage
Requires-Dist: google-cloud-storage (<3.0,>=1.32.0) ; extra == 'google-cloud-storage'
Provides-Extra: guesslang
Requires-Dist: guesslang ; extra == 'guesslang'
Provides-Extra: hf
Requires-Dist: huggingface-hub (<0.9.0,>=0.8.1) ; extra == 'hf'
Provides-Extra: html
Requires-Dist: html-to-json ; extra == 'html'
Provides-Extra: html-to-json
Requires-Dist: html-to-json ; extra == 'html-to-json'
Provides-Extra: huggingface-hub
Requires-Dist: huggingface-hub (<0.9.0,>=0.8.1) ; extra == 'huggingface-hub'
Provides-Extra: hwp
Requires-Dist: pyhwp ; extra == 'hwp'
Provides-Extra: jax
Requires-Dist: jax ; extra == 'jax'
Provides-Extra: joblib
Requires-Dist: joblib ; extra == 'joblib'
Provides-Extra: jsonlines
Requires-Dist: jsonlines ; extra == 'jsonlines'
Provides-Extra: jsonpath-ng
Requires-Dist: jsonpath-ng ; extra == 'jsonpath-ng'
Provides-Extra: kaleido
Requires-Dist: kaleido ; extra == 'kaleido'
Provides-Extra: label
Requires-Dist: cleanlab ; extra == 'label'
Requires-Dist: rubrix ; extra == 'label'
Provides-Extra: langdetect
Requires-Dist: fasttext-langdetect ; extra == 'langdetect'
Provides-Extra: loky
Requires-Dist: loky ; extra == 'loky'
Provides-Extra: lpips
Requires-Dist: lpips ; extra == 'lpips'
Provides-Extra: lsh
Requires-Dist: lsh ; extra == 'lsh'
Provides-Extra: mail
Requires-Dist: mail-parser ; extra == 'mail'
Provides-Extra: mail-parser
Requires-Dist: mail-parser ; extra == 'mail-parser'
Provides-Extra: matplotlib
Requires-Dist: matplotlib ; extra == 'matplotlib'
Provides-Extra: mecab
Requires-Dist: mecab-python3 ; extra == 'mecab'
Requires-Dist: mecab-ko-dic ; extra == 'mecab'
Provides-Extra: mecab-ko-dic
Requires-Dist: mecab-ko-dic ; extra == 'mecab-ko-dic'
Provides-Extra: mecab-python3
Requires-Dist: mecab-python3 ; extra == 'mecab-python3'
Provides-Extra: model
Requires-Dist: flaml ; extra == 'model'
Requires-Dist: datasets ; extra == 'model'
Requires-Dist: evaluate ; extra == 'model'
Requires-Dist: tensorflow ; extra == 'model'
Requires-Dist: accelerate ; extra == 'model'
Requires-Dist: scipy ; extra == 'model'
Requires-Dist: simpletransformers (>=0.63) ; extra == 'model'
Provides-Extra: modin
Requires-Dist: modin ; extra == 'modin'
Provides-Extra: namu-wiki-extractor
Requires-Dist: namu-wiki-extractor ; extra == 'namu-wiki-extractor'
Provides-Extra: nasdaq
Requires-Dist: nasdaq-data-link ; extra == 'nasdaq'
Provides-Extra: nasdaq-data-link
Requires-Dist: nasdaq-data-link ; extra == 'nasdaq-data-link'
Provides-Extra: nltk
Requires-Dist: nltk ; extra == 'nltk'
Provides-Extra: numba
Requires-Dist: numba ; extra == 'numba'
Provides-Extra: opencv-python
Requires-Dist: opencv-python (==4.5.5.64) ; extra == 'opencv-python'
Provides-Extra: openpyxl
Requires-Dist: openpyxl ; extra == 'openpyxl'
Provides-Extra: orjson
Requires-Dist: orjson ; extra == 'orjson'
Provides-Extra: p_tqdm
Requires-Dist: p-tqdm ; extra == 'p_tqdm'
Provides-Extra: parser
Requires-Dist: mail-parser ; extra == 'parser'
Requires-Dist: jsonpath-ng ; extra == 'parser'
Requires-Dist: p-tqdm ; extra == 'parser'
Requires-Dist: pysimdjson ; extra == 'parser'
Requires-Dist: jsonlines ; extra == 'parser'
Requires-Dist: pubmed-parser ; extra == 'parser'
Requires-Dist: namu-wiki-extractor ; extra == 'parser'
Requires-Dist: wikiextractor ; extra == 'parser'
Requires-Dist: pathos ; extra == 'parser'
Requires-Dist: beautifulsoup4 ; extra == 'parser'
Requires-Dist: joblib ; extra == 'parser'
Requires-Dist: cssutils ; extra == 'parser'
Requires-Dist: fasttext-langdetect ; extra == 'parser'
Requires-Dist: html-to-json ; extra == 'parser'
Requires-Dist: pdfplumber ; extra == 'parser'
Requires-Dist: loky ; extra == 'parser'
Requires-Dist: orjson ; extra == 'parser'
Requires-Dist: openpyxl ; extra == 'parser'
Requires-Dist: pyhwp ; extra == 'parser'
Provides-Extra: pathos
Requires-Dist: pathos ; extra == 'pathos'
Provides-Extra: pdfplumber
Requires-Dist: pdfplumber ; extra == 'pdfplumber'
Provides-Extra: plotly
Requires-Dist: plotly ; extra == 'plotly'
Provides-Extra: pubmed
Requires-Dist: pubmed-parser ; extra == 'pubmed'
Provides-Extra: pubmed_parser
Requires-Dist: pubmed-parser ; extra == 'pubmed_parser'
Provides-Extra: py7zr
Requires-Dist: py7zr ; extra == 'py7zr'
Provides-Extra: pyldavis
Requires-Dist: pyLDAvis ; extra == 'pyldavis'
Provides-Extra: pyhwp
Requires-Dist: pyhwp ; extra == 'pyhwp'
Provides-Extra: pymongo
Requires-Dist: pymongo ; extra == 'pymongo'
Provides-Extra: pynori
Requires-Dist: pynori ; extra == 'pynori'
Provides-Extra: pysbd
Requires-Dist: pysbd ; extra == 'pysbd'
Provides-Extra: pysimdjson
Requires-Dist: pysimdjson ; extra == 'pysimdjson'
Provides-Extra: ray
Requires-Dist: ray ; extra == 'ray'
Provides-Extra: rich
Requires-Dist: rich ; extra == 'rich'
Provides-Extra: rubrix
Requires-Dist: rubrix ; extra == 'rubrix'
Provides-Extra: sacremoses
Requires-Dist: sacremoses ; extra == 'sacremoses'
Provides-Extra: scipy
Requires-Dist: scipy ; extra == 'scipy'
Provides-Extra: seaborn
Requires-Dist: seaborn ; extra == 'seaborn'
Provides-Extra: simpletransformers
Requires-Dist: simpletransformers (>=0.63) ; extra == 'simpletransformers'
Provides-Extra: soynlp
Requires-Dist: soynlp ; extra == 'soynlp'
Provides-Extra: spacy
Requires-Dist: spacy ; extra == 'spacy'
Provides-Extra: stats
Requires-Dist: statsmodels ; extra == 'stats'
Provides-Extra: statsmodels
Requires-Dist: statsmodels ; extra == 'statsmodels'
Provides-Extra: tensorflow
Requires-Dist: tensorflow ; extra == 'tensorflow'
Provides-Extra: tensorflow-datasets
Requires-Dist: tensorflow-datasets ; extra == 'tensorflow-datasets'
Provides-Extra: timm
Requires-Dist: timm ; extra == 'timm'
Provides-Extra: tokenize
Requires-Dist: pysbd ; extra == 'tokenize'
Requires-Dist: mecab-ko-dic ; extra == 'tokenize'
Requires-Dist: spacy ; extra == 'tokenize'
Requires-Dist: pynori ; extra == 'tokenize'
Requires-Dist: mecab-python3 ; extra == 'tokenize'
Requires-Dist: sacremoses ; extra == 'tokenize'
Requires-Dist: emoji (<2.0) ; extra == 'tokenize'
Requires-Dist: soynlp ; extra == 'tokenize'
Requires-Dist: nltk ; extra == 'tokenize'
Requires-Dist: fugashi ; extra == 'tokenize'
Provides-Extra: tokenize-en
Requires-Dist: nltk ; extra == 'tokenize-en'
Requires-Dist: pysbd ; extra == 'tokenize-en'
Provides-Extra: tomotopy
Requires-Dist: tomotopy ; extra == 'tomotopy'
Provides-Extra: topic
Requires-Dist: wordcloud ; extra == 'topic'
Requires-Dist: pyLDAvis ; extra == 'topic'
Requires-Dist: tomotopy ; extra == 'topic'
Provides-Extra: transformers
Requires-Dist: datasets ; extra == 'transformers'
Requires-Dist: accelerate ; extra == 'transformers'
Requires-Dist: evaluate ; extra == 'transformers'
Requires-Dist: simpletransformers (>=0.63) ; extra == 'transformers'
Provides-Extra: unidecode
Requires-Dist: unidecode ; extra == 'unidecode'
Provides-Extra: visualize
Requires-Dist: matplotlib ; extra == 'visualize'
Requires-Dist: wordcloud ; extra == 'visualize'
Requires-Dist: kaleido ; extra == 'visualize'
Requires-Dist: rich ; extra == 'visualize'
Requires-Dist: seaborn ; extra == 'visualize'
Requires-Dist: plotly ; extra == 'visualize'
Requires-Dist: Pillow (<9.1.0) ; extra == 'visualize'
Provides-Extra: wget
Requires-Dist: wget ; extra == 'wget'
Provides-Extra: wiki
Requires-Dist: namu-wiki-extractor ; extra == 'wiki'
Requires-Dist: wikiextractor ; extra == 'wiki'
Provides-Extra: wikiextractor
Requires-Dist: wikiextractor ; extra == 'wikiextractor'
Provides-Extra: wordcloud
Requires-Dist: wordcloud ; extra == 'wordcloud'
Provides-Extra: xml
Requires-Dist: dicttoxml ; extra == 'xml'
Provides-Extra: yellowbrick
Requires-Dist: yellowbrick ; extra == 'yellowbrick'
Provides-Extra: zstandard
Requires-Dist: zstandard ; extra == 'zstandard'
